{"_ts":[1519893949],"_r":{"breakdown":{"html":{"bytes":[1923],"requests":[1]},"js":{"bytes":[31270],"requests":[1]},"css":{"bytes":[682],"requests":[1]},"image":{"bytes":[53],"requests":[1]},"flash":{"bytes":[0],"requests":[0]},"font":{"bytes":[0],"requests":[0]},"video":{"bytes":[0],"requests":[0]},"other":{"bytes":[62231],"requests":[3]}},"date":[1519893949],"domElements":[111],"domInteractive":[1141],"firstPaint":[1559],"fullyLoaded":[1880],"id":["180301_1Q_c064aa1e39a31cc6abb132e7d6b732f3"],"loadTime":[657],"render":[1081],"SpeedIndex":[1100],"TTFB":[204],"videoFrames":[[{"_i":"frame_0000.jpg","_t":0,"_vc":0},{"_i":"frame_0011.jpg","_t":1100,"_vc":100}]],"visualComplete":[1100],"lighthouse":[null],"pagespeed":[95]}}