{"_ts":[1512126695],"_r":{"breakdown":{"html":{"bytes":[3124],"requests":[1]},"js":{"bytes":[32447],"requests":[1]},"css":{"bytes":[1748],"requests":[1]},"image":{"bytes":[315],"requests":[1]},"flash":{"bytes":[0],"requests":[0]},"font":{"bytes":[0],"requests":[0]},"video":{"bytes":[0],"requests":[0]},"other":{"bytes":[65989],"requests":[3]}},"date":[1512126695],"domElements":[119],"domInteractive":[1078],"firstPaint":[1450],"fullyLoaded":[2290],"id":["171201_TM_1f7a459499ecf203ba919e50c4ef0156"],"loadTime":[1146],"render":[1496],"SpeedIndex":[1500],"TTFB":[624],"videoFrames":[[{"_i":"frame_0000.jpg","_t":0,"_vc":0},{"_i":"frame_0015.jpg","_t":1500,"_vc":100}]],"visualComplete":[1500],"lighthouse":[null],"pagespeed":[95]}}